pytest_rts/__init__.py
pytest_rts/plugin.py
pytest_rts/pytest/__init__.py
pytest_rts/pytest/fake_item.py
pytest_rts/pytest/runner_plugin.py
pytest_rts/utils/__init__.py
pytest_rts/utils/common.py
pytest_rts/utils/git.py
pytest_rts-2.5.0.dist-info/LICENSE.md
pytest_rts-2.5.0.dist-info/METADATA
pytest_rts-2.5.0.dist-info/WHEEL
pytest_rts-2.5.0.dist-info/entry_points.txt
pytest_rts-2.5.0.dist-info/top_level.txt
pytest_rts-2.5.0.dist-info/RECORD
