Metadata-Version: 2.1
Name: pytest-rts
Version: 2.5.0
Summary: Coverage-based regression test selection (RTS) plugin for pytest
Home-page: https://github.com/F-Secure/pytest-rts
Author: Eero Kauhanen, Matvey Pashkovskiy, Alexey Vyskubov
License: Apache License 2.0
Platform: any
Classifier: Programming Language :: Python
Classifier: Programming Language :: Python :: 3
Classifier: Programming Language :: Python :: 3.6
Classifier: Programming Language :: Python :: 3.7
Classifier: Programming Language :: Python :: 3.8
Classifier: Programming Language :: Python :: 3.9
Requires-Dist: coverage
Requires-Dist: pytest
Requires-Dist: pytest-cov
Requires-Dist: pydriller (>=2.0)
Provides-Extra: dev
Requires-Dist: pytest-socket ; extra == 'dev'
Requires-Dist: tox ; extra == 'dev'
Requires-Dist: python-semantic-release ; extra == 'dev'
Requires-Dist: black ; extra == 'dev'
Requires-Dist: mypy ; extra == 'dev'
Requires-Dist: pylint ; extra == 'dev'
Requires-Dist: safety ; extra == 'dev'
Requires-Dist: wheel ; extra == 'dev'
Requires-Dist: twine ; extra == 'dev'
Requires-Dist: xenon ; extra == 'dev'
